zget/__init__.py
zget/get.py
zget/put.py
zget/utils.py
zget-0.11.1.dist-info/DESCRIPTION.rst
zget-0.11.1.dist-info/METADATA
zget-0.11.1.dist-info/RECORD
zget-0.11.1.dist-info/WHEEL
zget-0.11.1.dist-info/entry_points.txt
zget-0.11.1.dist-info/metadata.json
zget-0.11.1.dist-info/top_level.txt
